pyvdo/__init__.py
pyvdo/__main__.py
pyvdo/__version__.py
pyvdo/playlist.py
pyvdo-0.0.6.dist-info/METADATA
pyvdo-0.0.6.dist-info/WHEEL
pyvdo-0.0.6.dist-info/entry_points.txt
pyvdo-0.0.6.dist-info/top_level.txt
pyvdo-0.0.6.dist-info/RECORD
